[{"Id":1,"Name":"asd","Type":"asd","PlateNumber":"AAA-000","ManufactureYear":1999,"WorkCategory":"Engine","Description":"asd","Seriousness":1,"Status":"Open","WorkHourEstimation":3.2},{"Id":2,"Name":"Kiss L\u00E1szl\u00F3","Type":"BMW E60 530D","PlateNumber":"KRK-745","ManufactureYear":2005,"WorkCategory":"Engine","Description":"Oil Change","Seriousness":2,"Status":"In Progress","WorkHourEstimation":2.4},{"Id":3,"Name":"Zambo Jimmy","Type":"BMW","PlateNumber":"ASD-123","ManufactureYear":142,"WorkCategory":"Suspension","Description":"asd","Seriousness":3,"Status":"In Progress","WorkHourEstimation":4.8},{"Id":4,"Name":"Cristiano Ronaldo","Type":"Rolls Royce ","PlateNumber":"RON-007","ManufactureYear":2012,"WorkCategory":"Chassis","Description":"as","Seriousness":10,"Status":"Completed","WorkHourEstimation":4.5}]